keepersdk/__init__.py
keepersdk/background.py
keepersdk/constants.py
keepersdk/crypto.py
keepersdk/errors.py
keepersdk/generator.py
keepersdk/py.typed
keepersdk/sqlite_dao.py
keepersdk/utils.py
keepersdk/authentication/__init__.py
keepersdk/authentication/auth_utils.py
keepersdk/authentication/breachwatch.py
keepersdk/authentication/configuration.py
keepersdk/authentication/endpoint.py
keepersdk/authentication/keeper_auth.py
keepersdk/authentication/login_auth.py
keepersdk/authentication/notifications.py
keepersdk/authentication/yubikey.py
keepersdk/enterprise/__init__.py
keepersdk/enterprise/account_transfer.py
keepersdk/enterprise/audit_report.py
keepersdk/enterprise/batch_management.py
keepersdk/enterprise/enterprise_constants.py
keepersdk/enterprise/enterprise_data.py
keepersdk/enterprise/enterprise_loader.py
keepersdk/enterprise/enterprise_management.py
keepersdk/enterprise/enterprise_types.py
keepersdk/enterprise/enterprise_user_management.py
keepersdk/enterprise/msp_auth.py
keepersdk/enterprise/private_data.py
keepersdk/enterprise/sqlite_enterprise_storage.py
keepersdk/importer/__init__.py
keepersdk/importer/import_data.py
keepersdk/importer/import_utils.py
keepersdk/importer/keeper_format.py
keepersdk/plugins/__init__.py
keepersdk/plugins/pedm/__init__.py
keepersdk/plugins/pedm/admin_plugin.py
keepersdk/plugins/pedm/admin_storage.py
keepersdk/plugins/pedm/admin_types.py
keepersdk/plugins/pedm/pedm_shared.py
keepersdk/plugins/sox/__init__.py
keepersdk/plugins/sox/sox_storage.py
keepersdk/proto/APIRequest_pb2.py
keepersdk/proto/APIRequest_pb2.pyi
keepersdk/proto/AccountSummary_pb2.py
keepersdk/proto/AccountSummary_pb2.pyi
keepersdk/proto/BI_pb2.py
keepersdk/proto/BI_pb2.pyi
keepersdk/proto/GraphSync_pb2.py
keepersdk/proto/GraphSync_pb2.pyi
keepersdk/proto/NotificationCenter_pb2.py
keepersdk/proto/NotificationCenter_pb2.pyi
keepersdk/proto/SyncDown_pb2.py
keepersdk/proto/SyncDown_pb2.pyi
keepersdk/proto/__init__.py
keepersdk/proto/automator_pb2.py
keepersdk-1.0.1.dist-info/METADATA
keepersdk-1.0.1.dist-info/WHEEL
keepersdk-1.0.1.dist-info/top_level.txt
keepersdk-1.0.1.dist-info/RECORD
